readline.py
override_readline.py
gnureadline.cpython-313-darwin.so
gnureadline-8.3.3.dist-info/RECORD
gnureadline-8.3.3.dist-info/WHEEL
gnureadline-8.3.3.dist-info/top_level.txt
gnureadline-8.3.3.dist-info/METADATA
gnureadline-8.3.3.dist-info/licenses/LICENSE
