Metadata-Version: 2.1
Name: gnureadline
Version: 8.3.3
Summary: The standard Python readline extension statically linked against the GNU readline library.
Home-page: http://github.com/ludwigschwardt/python-gnureadline
Maintainer: Ludwig Schwardt, Sridhar Ratnakumar
Maintainer-email: ludwig.schwardt@gmail.com, srid@srid.ca
License: GPL-3.0-or-later
Classifier: Development Status :: 5 - Production/Stable
Classifier: Environment :: Console
Classifier: Intended Audience :: Developers
Classifier: Intended Audience :: End Users/Desktop
Classifier: Operating System :: MacOS :: MacOS X
Classifier: Operating System :: POSIX
Classifier: Programming Language :: C
Classifier: Programming Language :: Python :: 2
Classifier: Programming Language :: Python :: 3
Classifier: Topic :: Software Development :: Libraries :: Python Modules
License-File: LICENSE
